ms2binner/__init__.py
ms2binner/bin.py
ms2binner/conf.py
ms2binner/main.py
ms2binner/test_binner.py
ms2binner/visualization.py
ms2binner-1.0.17.dist-info/LICENSE
ms2binner-1.0.17.dist-info/METADATA
ms2binner-1.0.17.dist-info/WHEEL
ms2binner-1.0.17.dist-info/top_level.txt
ms2binner-1.0.17.dist-info/RECORD
