Metadata-Version: 2.1
Name: ms2binner
Version: 1.0.17
Summary: Filters and bins ms2 spectra
Home-page: https://github.com/askerdb/ms2binner
Author: Asker Brejnrod & Arjun Sampath
License: Apache Software License 2.0
Platform: UNKNOWN
Classifier: Programming Language :: Python :: 3
Classifier: License :: OSI Approved :: MIT License
Classifier: Operating System :: OS Independent
Provides-Extra: dev
Requires-Dist: sphinxcontrib-apidoc ; extra == 'dev'
Requires-Dist: pytest ; extra == 'dev'
